Aula02/PraticaIV/cafe.v
module cafe (input coffe_button, money, soup_button, output reg coffee, soup);
    always @(coffe_button or money or soup_button) begin
        coffee <= (~(coffe_button & soup_button) & (coffe_button & money));
        soup <= (money & soup_button);
    end
endmodule


module test;
    reg c, m, s;
    wire coffee, soup;
    integer i;

    cafe a (.coffe_button(c), .money(m), .soup_button(s), .coffee(coffee), .soup(soup));

    initial begin
        c <= 0;
        m <= 0;
        s <= 0;

        $monitor("\Coffee Button: %0b\t\tMoney: %0b\t\tSoup Button: %0b\t\tCoffe: %0b\t\tSoup: %0b\n", c, m, s, coffee, soup);
        $dumpfile("coffee.vcd"); // Definindo o nome do arquivo para o gtkwave
        $dumpvars(0, test);

        for (i = 0; i < 8 ; i = i + 1) begin
            {c, m, s} = i;
            #10;
        end
    end
endmodule

Aula02/PraticaIV/coffee.vcd
$date
	Fri Nov 10 15:03:43 2023
$end
$version
	Icarus Verilog
$end
$timescale
	1s
$end
$scope module test $end
$var wire 1 ! soup $end
$var wire 1 " coffee $end
$var reg 1 # c $end
$var reg 1 $ m $end
$var reg 1 % s $end
$var integer 32 & i [31:0] $end
$scope module a $end
$var wire 1 # coffe_button $end
$var wire 1 $ money $end
$var wire 1 % soup_button $end
$var reg 1 " coffee $end
$var reg 1 ! soup $end
$upscope $end
$upscope $end
$enddefinitions $end
$comment Show the parameter values. $end
$dumpall
$end
#0
$dumpvars
b0 &
0%
0$
0#
0"
0!
$end
#10
1%
b1 &
#20
1$
0%
b10 &
#30
1!
1%
b11 &
#40
0!
1#
0$
0%
b100 &
#50
1%
b101 &
#60
1"
1$
0%
b110 &
#70
1!
0"
1%
b111 &
#80
b1000 &
