Aula02/PraticaIII/alarme.v
module alarme(input motorista_presente, cinto_em_uso, ignicao_ligada, output reg luz_de_advertencia);

    always @(motorista_presente or cinto_em_uso or ignicao_ligada) begin

        luz_de_advertencia <= (motorista_presente & (~cinto_em_uso) & ignicao_ligada);

    end

endmodule


module test;
    reg motorista, cinto, ignicao;
    wire luz;
    integer i;

    alarme a (.motorista_presente(motorista), .cinto_em_uso(cinto), .ignicao_ligada(ignicao), .luz_de_advertencia(luz));

    initial begin
        motorista <= 0;
        cinto <= 0;
        ignicao <= 0;

        $monitor("\nMotorista: %0b\t\tCinto: %0b\t\tIgnicao: %0b\t\tLuz de Advertencia: %0b\n", motorista, cinto, ignicao, luz);
        $dumpfile("alarm.vcd"); // Definindo o nome do arquivo para o gtkwave
        $dumpvars(0, test);

        for (i = 0; i < 8 ; i = i + 1) begin
            {motorista, cinto, ignicao} = i;
            #10;
        end

    end

endmodule

Aula02/PraticaIII/alarm.vcd
$date
	Fri Nov 10 14:56:32 2023
$end
$version
	Icarus Verilog
$end
$timescale
	1s
$end
$scope module test $end
$var wire 1 ! luz $end
$var reg 1 " cinto $end
$var reg 1 # ignicao $end
$var reg 1 $ motorista $end
$var integer 32 % i [31:0] $end
$scope module a $end
$var wire 1 " cinto_em_uso $end
$var wire 1 # ignicao_ligada $end
$var wire 1 $ motorista_presente $end
$var reg 1 ! luz_de_advertencia $end
$upscope $end
$upscope $end
$enddefinitions $end
$comment Show the parameter values. $end
$dumpall
$end
#0
$dumpvars
b0 %
0$
0#
0"
0!
$end
#10
1#
b1 %
#20
1"
0#
b10 %
#30
1#
b11 %
#40
1$
0"
0#
b100 %
#50
1!
1#
b101 %
#60
0!
1"
0#
b110 %
#70
1#
b111 %
#80
b1000 %
