Aula02/PraticaI/combo.v
module combo (input a, b, c, d, output reg o);
    always @(a or b or c or d) begin
        o <= ~((a & b) | (c ^ d));
    end
endmodule


module test;
    reg a, b, c, d;
    wire o;
    integer i;

    combo c1 (.a(a), .b(b), .c(c), .d(d), .o(o));

    initial begin
        a <= 0;
        b <= 0;
        c <= 0;
        d <= 0;

        $monitor("a: %b b: %b c: %b d: %b o: %b", a, b, c, d, o);
        $dumpfile("comb.vcd"); // Definindo o nome do arquivo para o gtkwave
        $dumpvars(0, test); // Fala quais variáveis eu quero enviar e qual o nome do modulo de teste

        for (i = 0;i < 16 ;i = i + 1) begin
            {a, b, c, d} = i;
            #10;
        end
    end

    

endmodule

Aula02/PraticaI/comb.vcd
$date
	Fri Nov 10 14:07:12 2023
$end
$version
	Icarus Verilog
$end
$timescale
	1s
$end
$scope module test $end
$var wire 1 ! o $end
$var reg 1 " a $end
$var reg 1 # b $end
$var reg 1 $ c $end
$var reg 1 % d $end
$var integer 32 & i [31:0] $end
$scope module c1 $end
$var wire 1 " a $end
$var wire 1 # b $end
$var wire 1 $ c $end
$var wire 1 % d $end
$var reg 1 ! o $end
$upscope $end
$upscope $end
$enddefinitions $end
$comment Show the parameter values. $end
$dumpall
$end
#0
$dumpvars
b0 &
0%
0$
0#
0"
1!
$end
#10
0!
1%
b1 &
#20
1$
0%
b10 &
#30
1!
1%
b11 &
#40
1#
0$
0%
b100 &
#50
0!
1%
b101 &
#60
1$
0%
b110 &
#70
1!
1%
b111 &
#80
1"
0#
0$
0%
b1000 &
#90
0!
1%
b1001 &
#100
1$
0%
b1010 &
#110
1!
1%
b1011 &
#120
0!
1#
0$
0%
b1100 &
#130
1%
b1101 &
#140
1$
0%
b1110 &
#150
1%
b1111 &
#160
b10000 &
