Aula02/PraticaII/mod10_counter.v
module mod10_counter (input clk, input rstn, output reg[3:0] out);
    always @(posedge clk) begin
        if (!rstn) begin
            out <= 0;
        end else begin
            if (out == 10) 
                out <= 0;
            else
                out <= out + 1;
        end
    end
endmodule


module test;
    reg clk, rstn;
    wire[3:0] out;
    
    always #2 clk = ~clk;

    mod10_counter c1 (.clk(clk), .rstn(rstn), .out(out));

    initial begin

        $monitor("clk= %0b\trstn= %0b\tout= %b\n", clk, rstn, out);
        $dumpfile("mod10_counter.vcd"); // Definindo o nome do arquivo para o gtkwave
        $dumpvars(0, test); // Fala quais variáveis eu quero enviar e qual o nome do modulo de teste

        {clk, rstn} = 0;

        #2 rstn <= 1;

        #100 $finish;

    end

endmodule

Aula02/PraticaII/mod10_counter.vcd
$date
	Fri Nov 10 14:39:56 2023
$end
$version
	Icarus Verilog
$end
$timescale
	1s
$end
$scope module test $end
$var wire 4 ! out [3:0] $end
$var reg 1 " clk $end
$var reg 1 # rstn $end
$scope module c1 $end
$var wire 1 " clk $end
$var wire 1 # rstn $end
$var reg 4 $ out [3:0] $end
$upscope $end
$upscope $end
$enddefinitions $end
$comment Show the parameter values. $end
$dumpall
$end
#0
$dumpvars
bx $
0#
0"
bx !
$end
#2
b0 !
b0 $
1#
1"
#4
0"
#6
b1 !
b1 $
1"
#8
0"
#10
b10 !
b10 $
1"
#12
0"
#14
b11 !
b11 $
1"
#16
0"
#18
b100 !
b100 $
1"
#20
0"
#22
b101 !
b101 $
1"
#24
0"
#26
b110 !
b110 $
1"
#28
0"
#30
b111 !
b111 $
1"
#32
0"
#34
b1000 !
b1000 $
1"
#36
0"
#38
b1001 !
b1001 $
1"
#40
0"
#42
b1010 !
b1010 $
1"
#44
0"
#46
b0 !
b0 $
1"
#48
0"
#50
b1 !
b1 $
1"
#52
0"
#54
b10 !
b10 $
1"
#56
0"
#58
b11 !
b11 $
1"
#60
0"
#62
b100 !
b100 $
1"
#64
0"
#66
b101 !
b101 $
1"
#68
0"
#70
b110 !
b110 $
1"
#72
0"
#74
b111 !
b111 $
1"
#76
0"
#78
b1000 !
b1000 $
1"
#80
0"
#82
b1001 !
b1001 $
1"
#84
0"
#86
b1010 !
b1010 $
1"
#88
0"
#90
b0 !
b0 $
1"
#92
0"
#94
b1 !
b1 $
1"
#96
0"
#98
b10 !
b10 $
1"
#100
0"
#102
b11 !
b11 $
1"
